fast_unzip/__init__.py
fast_unzip/__main__.py
fast_unzip/custom_exceptions.py
fast_unzip/fast_unzip.py
fast_unzip-1.3.2.dist-info/METADATA
fast_unzip-1.3.2.dist-info/WHEEL
fast_unzip-1.3.2.dist-info/LICENSE
fast_unzip-1.3.2.dist-info/entry_points.txt
fast_unzip-1.3.2.dist-info/RECORD
