Metadata-Version: 2.1
Name: fast-unzip
Version: 1.3.2
Summary: Fast multithread/multiprocess unzipper
Home-page: https://github.com/Inferno2899/fast_unzip.git
License: MIT
Author: Nikita Pshenko
Author-email: pshenko1999@gmail.com
Requires-Python: >=3.8,<4.0
Classifier: License :: OSI Approved :: MIT License
Classifier: Operating System :: OS Independent
Classifier: Programming Language :: Python :: 3
Classifier: Programming Language :: Python :: 3.8
Classifier: Programming Language :: Python :: 3.9
Classifier: Programming Language :: Python :: 3.10
Classifier: Programming Language :: Python :: 3.11
Classifier: Programming Language :: Python :: 3
Project-URL: Repository, https://github.com/Inferno2899/fast_unzip.git
